setup.cfg
setup.py
pyterminal/__init__.py
pyterminal/pyterminal.py
pyterminal.egg-info/PKG-INFO
pyterminal.egg-info/SOURCES.txt
pyterminal.egg-info/dependency_links.txt
pyterminal.egg-info/not-zip-safe
pyterminal.egg-info/top_level.txt