Metadata-Version: 1.0
Name: pyterminal
Version: 0.4
Summary: Make your text appear with the speed of normal handwriting
Home-page: http://github.com/dr34mwh1t3/pyterminal
Author: Dreamwhite
Author-email: officialdreamwhite@gmail.com
License: GPL
Platform: UNKNOWN
